logipar/__init__.py
logipar/logipar.py
logipar-0.6.0.dist-info/LICENSE
logipar-0.6.0.dist-info/METADATA
logipar-0.6.0.dist-info/WHEEL
logipar-0.6.0.dist-info/top_level.txt
logipar-0.6.0.dist-info/RECORD
