Metadata-Version: 2.1
Name: logipar
Version: 0.6.0
Summary: A logic string parser
Home-page: https://github.com/altef/logipar
Author: Brad Gill
Author-email: brad@alteredeffect.com
License: UNKNOWN
Platform: UNKNOWN
Classifier: Programming Language :: Python :: 3
Classifier: License :: OSI Approved :: MIT License
Classifier: Operating System :: OS Independent
